test.py
minRL/ppo.py
minRL/spin_ppo.py
minRL/utils.py
minRL-0.0.6.dist-info/LICENSE
minRL-0.0.6.dist-info/METADATA
minRL-0.0.6.dist-info/WHEEL
minRL-0.0.6.dist-info/top_level.txt
minRL-0.0.6.dist-info/RECORD
