Metadata-Version: 2.1
Name: minRL
Version: 0.0.6
Summary: Deep Reinforcement Learning for minimalists.
Author-email: Ricky Ding <e0134117@u.nus.edu>
Project-URL: Homepage, https://github.com/tesla-cat/minRL
Project-URL: Issues, https://github.com/tesla-cat/minRL/issues
Classifier: Programming Language :: Python :: 3
Classifier: License :: OSI Approved :: MIT License
Classifier: Operating System :: OS Independent
Requires-Python: >=3.8
License-File: LICENSE
